tidylog/__init__.py
tidylog/_version.py
tidylog/formatter.py
tidylog/livekit.py
tidylog/logger.py
tidylog-0.1.2.dist-info/METADATA
tidylog-0.1.2.dist-info/WHEEL
tidylog-0.1.2.dist-info/licenses/LICENSE
tidylog-0.1.2.dist-info/RECORD
