Metadata-Version: 2.4
Name: tidylog
Version: 0.1.2
Summary: Clean, colorized structured logging for Python with JSON extra fields
Project-URL: Repository, https://github.com/param-ai/tidylog.git
Author: Ayush Joshi
License-Expression: MIT
License-File: LICENSE
Keywords: colorized,formatter,json,logging,structured-logging
Classifier: Development Status :: 4 - Beta
Classifier: Intended Audience :: Developers
Classifier: License :: OSI Approved :: MIT License
Classifier: Operating System :: OS Independent
Classifier: Programming Language :: Python :: 3
Classifier: Programming Language :: Python :: 3.9
Classifier: Programming Language :: Python :: 3.10
Classifier: Programming Language :: Python :: 3.11
Classifier: Programming Language :: Python :: 3.12
Classifier: Programming Language :: Python :: 3.13
Classifier: Topic :: Software Development :: Libraries :: Python Modules
Classifier: Topic :: System :: Logging
Classifier: Typing :: Typed
Requires-Python: >=3.9
Provides-Extra: livekit
Requires-Dist: livekit-agents; extra == 'livekit'
